LICENSE
MANIFEST.in
README.rst
requirements_dev.txt
setup.cfg
setup.py
gsch/__init__.py
gsch/agent.py
gsch/option.py
gsch/paper.py
gsch.egg-info/PKG-INFO
gsch.egg-info/SOURCES.txt
gsch.egg-info/dependency_links.txt
gsch.egg-info/not-zip-safe
gsch.egg-info/requires.txt
gsch.egg-info/top_level.txt
tests/__init__.py
tests/test_agent.py
tests/test_paper.py