Metadata-Version: 1.1
Name: gsch
Version: 0.2.3
Summary: gsch is a tool for handling paper information in a Google Scholar results page.
Home-page: https://github.com/jun-harashima/gsch
Author: Jun Harashima
Author-email: j.harashima@gmail.com
License: MIT license
Keywords: gsch
Platform: UNKNOWN
Classifier: Development Status :: 2 - Pre-Alpha
Classifier: Intended Audience :: Developers
Classifier: License :: OSI Approved :: MIT License
Classifier: Natural Language :: English
Classifier: Programming Language :: Python :: 2
Classifier: Programming Language :: Python :: 2.7
Classifier: Programming Language :: Python :: 3
Classifier: Programming Language :: Python :: 3.4
Classifier: Programming Language :: Python :: 3.5
Classifier: Programming Language :: Python :: 3.6
Classifier: Programming Language :: Python :: 3.7
